AUTHORS
ChangeLog
LICENSE
MANIFEST.in
NOTICE
README.md
requirements.txt
setup.cfg
setup.py
elver/__init__.py
elver/docker_build.py
elver.egg-info/PKG-INFO
elver.egg-info/SOURCES.txt
elver.egg-info/dependency_links.txt
elver.egg-info/not-zip-safe
elver.egg-info/pbr.json
elver.egg-info/requires.txt
elver.egg-info/top_level.txt