Metadata-Version: 1.1
Name: elver
Version: 0.1.0
Summary: Package python app in Docker with ease
Home-page: https://github.com/ravwojdyla/elver
Author: UNKNOWN
Author-email: UNKNOWN
License: Apache-2
Keywords: distutils
Platform: UNKNOWN
Classifier: Development Status :: 3 - Alpha
Classifier: Intended Audience :: Developers
Classifier: Intended Audience :: Information Technology
Classifier: License :: OSI Approved :: Apache Software License
Classifier: Operating System :: OS Independent
Classifier: Programming Language :: Python
Classifier: Programming Language :: Python :: 2.7
Classifier: Programming Language :: Python :: 3
Classifier: Programming Language :: Python :: 3.2
Classifier: Programming Language :: Python :: 3.3
Classifier: Programming Language :: Python :: 3.4
